MANIFEST.in
README.md
setup.cfg
setup.py
versioneer.py
happer/__init__.py
happer/__main__.py
happer/_version.py
happer/allele.py
happer/mutablestring.py
happer/mutate.py
happer/seqio.py
happer.egg-info/PKG-INFO
happer.egg-info/SOURCES.txt
happer.egg-info/dependency_links.txt
happer.egg-info/entry_points.txt
happer.egg-info/top_level.txt
happer.egg-info/zip-safe
happer/tests/__init__.py
happer/tests/test_allele.py
happer/tests/test_mutablestring.py
happer/tests/test_mutate.py
happer/tests/test_seqio.py