Metadata-Version: 2.1
Name: happer
Version: 0.1.0
Summary: Library for applying haplotypes to reference DNA sequences
Home-page: https://github.com/bioforensics/happer
Author: Daniel Standage
Author-email: daniel.standage@nbacc.dhs.gov
License: UNKNOWN
Platform: UNKNOWN
Classifier: Environment :: Console
Classifier: Framework :: IPython
Classifier: Framework :: Jupyter
Classifier: Intended Audience :: Science/Research
Classifier: License :: OSI Approved :: BSD License
Classifier: Programming Language :: Python :: 3
Classifier: Topic :: Scientific/Engineering :: Bio-Informatics
